Metadata-Version: 2.1
Name: pangoro
Version: 0.32
Summary: pangoro python package
Home-page: https://github.com/ieuTeamD
Author: Team D
Author-email: ieuTeamD@gmail.com
License: MIT
Platform: UNKNOWN
License-File: LICENSE.txt
